dwf_sim/__init__.py
dwf_sim/benchmark.py
dwf_sim/benchmark_pins.py
dwf_sim/cli.py
dwf_sim/data_files.py
dwf_sim/main.py
dwf_sim/matrix_context.py
dwf_sim/pool.py
dwf_sim/sample_1kg.py
dwf_sim/simulate.py
dwf_sim/utils.py
dwf_sim/vcf_utils.py
dwf_sim/bin/darwin-arm64/ngsngs
dwf_sim/bin/linux-x86_64/ngsngs
dwf_sim/data/AccFreqL150R1.txt
dwf_sim/data/AccFreqL150R2.txt
dwf_sim/data/__init__.py
dwf_sim/data/small_reference.dict
dwf_sim/data/small_reference.fna
dwf_sim/data/small_reference.fna.0123
dwf_sim/data/small_reference.fna.amb
dwf_sim/data/small_reference.fna.ann
dwf_sim/data/small_reference.fna.bwt
dwf_sim/data/small_reference.fna.bwt.2bit.64
dwf_sim/data/small_reference.fna.fai
dwf_sim/data/small_reference.fna.pac
dwf_sim/data/small_reference.fna.sa
dwf_sim/data/target_calling.bed
dwf_sim/data/small_reference.sdf/done
dwf_sim/data/small_reference.sdf/format.log
dwf_sim/data/small_reference.sdf/mainIndex
dwf_sim/data/small_reference.sdf/nameIndex0
dwf_sim/data/small_reference.sdf/namedata0
dwf_sim/data/small_reference.sdf/namepointer0
dwf_sim/data/small_reference.sdf/progress
dwf_sim/data/small_reference.sdf/seqdata0
dwf_sim/data/small_reference.sdf/seqpointer0
dwf_sim/data/small_reference.sdf/sequenceIndex0
dwf_sim/data/small_reference.sdf/summary.txt
dwf_sim-0.1.1.dist-info/METADATA
dwf_sim-0.1.1.dist-info/WHEEL
dwf_sim-0.1.1.dist-info/entry_points.txt
dwf_sim-0.1.1.dist-info/licenses/LICENSE
dwf_sim-0.1.1.dist-info/RECORD
