Metadata-Version: 2.4
Name: dwf-sim
Version: 0.1.1
Summary: Simulate two-dimensional overlapped pool sequencing data
Project-URL: Homepage, https://github.com/madscort/dwf-sim
Project-URL: Repository, https://github.com/madscort/dwf-sim.git
Project-URL: Issues, https://github.com/madscort/dwf-sim/issues
Author-email: Mads Nielsen <madsn@msn.com>
License: MIT License
License-File: LICENSE
Classifier: Development Status :: 3 - Alpha
Classifier: Intended Audience :: Science/Research
Classifier: License :: OSI Approved :: MIT License
Classifier: Programming Language :: Python :: 3
Classifier: Programming Language :: Python :: 3.10
Classifier: Topic :: Scientific/Engineering :: Bio-Informatics
Requires-Python: <3.11,>=3.10
Requires-Dist: pandas>=1.0
Requires-Dist: pysam>=0.19
Provides-Extra: dev
Requires-Dist: pytest-cov>=4.0; extra == 'dev'
Requires-Dist: pytest>=7.0; extra == 'dev'
Requires-Dist: ruff>=0.1.0; extra == 'dev'
